py_dsa/algorithms.py
py_dsa/data_structures.py
py_dsa-0.0.3.dist-info/LICENSE
py_dsa-0.0.3.dist-info/METADATA
py_dsa-0.0.3.dist-info/WHEEL
py_dsa-0.0.3.dist-info/top_level.txt
py_dsa-0.0.3.dist-info/RECORD
