Metadata-Version: 2.1
Name: py-dsa
Version: 0.0.3
Summary: The py_dsa package contains all the data structures and algorithms implementations
Home-page: https://github.com/smv1999/py_dsa
Author: Vaidhyanathan S M
Author-email: vaidhyanathan.sm@gmail.com
License: UNKNOWN
Platform: UNKNOWN
Classifier: Programming Language :: Python :: 3
Classifier: Programming Language :: Python :: 3.7
Classifier: Programming Language :: Python :: 3.8
Classifier: Topic :: Software Development :: Libraries :: Python Modules
Classifier: License :: OSI Approved :: MIT License
Classifier: Operating System :: OS Independent
Requires-Python: >=3
Provides-Extra: dev
Requires-Dist: check-manifest ; extra == 'dev'
Requires-Dist: pytest (>=3.7) ; extra == 'dev'
Requires-Dist: twine ; extra == 'dev'
